pynobo.py
pynobo-1.8.1.dist-info/LICENSE
pynobo-1.8.1.dist-info/METADATA
pynobo-1.8.1.dist-info/WHEEL
pynobo-1.8.1.dist-info/top_level.txt
pynobo-1.8.1.dist-info/RECORD
