Metadata-Version: 2.1
Name: pynobo
Version: 1.8.1
Summary: Nobø Hub / Nobø Energy Control TCP/IP Interface
Home-page: https://github.com/echoromeo/pynobo
Author: echoromeo, capelevy, oyvindwe
License: GPLv3+
Project-URL: Bug Reports, https://github.com/echoromeo/pynobo/issues
Project-URL: Source, https://github.com/echoromeo/pynobo/blob/master/pynobo.py
Keywords: hvac nobø heating automation
Classifier: Development Status :: 5 - Production/Stable
Classifier: Intended Audience :: Developers
Classifier: Topic :: Home Automation
Classifier: License :: OSI Approved :: GNU General Public License v3 or later (GPLv3+)
Classifier: Programming Language :: Python :: 3
Classifier: Programming Language :: Python :: 3 :: Only
Requires-Python: >=3.7, <4
License-File: LICENSE
